ldv/__init__.py
ldv/__main__.py
ldv/commands/__init__.py
ldv/commands/auth.py
ldv/commands/init.py
ldv/commands/versioning.py
ldv/constants/__init__.py
ldv/constants/auth.py
ldv/constants/config.py
ldv/constants/remote.py
ldv/constants/versioning.py
ldv/core/__init__.py
ldv/core/init.py
ldv/core/versioning.py
ldv/dto/__init__.py
ldv/dto/auth.py
ldv/dto/config.py
ldv/dto/digest.py
ldv/enums/__init__.py
ldv/enums/auth.py
ldv/enums/remote.py
ldv/remote/__init__.py
ldv/remote/base.py
ldv/remote/auth/__init__.py
ldv/remote/auth/aws.py
ldv/remote/auth/base.py
ldv/remote/client/__init__.py
ldv/remote/client/aws.py
ldv/remote/client/base.py
ldv/remote/storage/__init__.py
ldv/remote/storage/aws.py
ldv/remote/storage/base.py
ldv/utils/__init__.py
ldv/utils/aws_config.py
ldv/utils/cache_helper.py
ldv/utils/config.py
ldv/utils/constants_helper.py
ldv/utils/digest_helper.py
ldv/utils/exceptions.py
ldv/utils/url_helper.py
ldv/utils/validation.py
ldv-0.1.5.dist-info/METADATA
ldv-0.1.5.dist-info/WHEEL
ldv-0.1.5.dist-info/entry_points.txt
ldv-0.1.5.dist-info/top_level.txt
ldv-0.1.5.dist-info/RECORD
