Metadata-Version: 2.1
Name: ldv
Version: 0.1.5
Summary: Light Data Versioning
Home-page: https://github.com/martinnorin/ldv
Author: Martin Neumann
Author-email: ldv@martinneumann.se
Classifier: Programming Language :: Python :: 3
Classifier: License :: OSI Approved :: MIT License
Classifier: Operating System :: OS Independent
Requires-Python: >=3.10
Requires-Dist: boto3
Requires-Dist: click
Requires-Dist: python-dateutil
